tokenmeter/__init__.py
tokenmeter/calculator.py
tokenmeter/models.py
tokenmeter/utils.py
tokenmeter-0.1.0.dist-info/LICENSE
tokenmeter-0.1.0.dist-info/METADATA
tokenmeter-0.1.0.dist-info/WHEEL
tokenmeter-0.1.0.dist-info/top_level.txt
tokenmeter-0.1.0.dist-info/RECORD
