Metadata-Version: 2.1
Name: tokenmeter
Version: 0.1.0
Summary: A library for calculating and estimating costs of language model usage
Home-page: https://github.com/rehan-ai/tokenmeter
Author: Rehan Asif
Author-email: Rehan Asif <asif.rehan@icloud.com>
Project-URL: Homepage, https://github.com/rehan-ai/tokenmeter
Project-URL: Bug Tracker, https://github.com/rehan-ai/tokenmeter/issues
Keywords: nlp,language models,cost estimation,openai
Classifier: Development Status :: 3 - Alpha
Classifier: Intended Audience :: Developers
Classifier: License :: OSI Approved :: MIT License
Classifier: Programming Language :: Python :: 3
Classifier: Programming Language :: Python :: 3.6
Classifier: Programming Language :: Python :: 3.7
Classifier: Programming Language :: Python :: 3.8
Classifier: Programming Language :: Python :: 3.9
Requires-Python: >=3.6
License-File: LICENSE
Requires-Dist: requests
Requires-Dist: tiktoken
Requires-Dist: openai
Provides-Extra: dev
Requires-Dist: pytest ; extra == 'dev'
Requires-Dist: black ; extra == 'dev'
Requires-Dist: isort ; extra == 'dev'
Requires-Dist: flake8 ; extra == 'dev'
